distributions/Binomialdistribution.py
distributions/Gaussiandistributions.py
distributions/Generaldistribution.py
distributions/__init__.py
nano_degree_MLE_dist_2-0.1.dist-info/METADATA
nano_degree_MLE_dist_2-0.1.dist-info/WHEEL
nano_degree_MLE_dist_2-0.1.dist-info/top_level.txt
nano_degree_MLE_dist_2-0.1.dist-info/RECORD
